json_schema_enforcer/__init__.py
json_schema_enforcer/py.typed
json_schema_enforcer/schema.py
json_schema_enforcer-0.1.4.dist-info/METADATA
json_schema_enforcer-0.1.4.dist-info/WHEEL
json_schema_enforcer-0.1.4.dist-info/RECORD
