Metadata-Version: 2.1
Name: json-schema-enforcer
Version: 0.1.4
Summary: A progressive JSON schema validator
Author: rizerphe
Author-email: 44440399+rizerphe@users.noreply.github.com
Requires-Python: >=3.10,<4.0
Classifier: Programming Language :: Python :: 3
Classifier: Programming Language :: Python :: 3.10
Classifier: Programming Language :: Python :: 3.11
